partialmethod.py
smartcompose.py
smartcompose-0.1.2.dist-info/metadata.json
smartcompose-0.1.2.dist-info/DESCRIPTION.rst
smartcompose-0.1.2.dist-info/WHEEL
smartcompose-0.1.2.dist-info/RECORD
smartcompose-0.1.2.dist-info/METADATA
smartcompose-0.1.2.dist-info/top_level.txt
