Metadata-Version: 2.0
Name: smartcompose
Version: 0.1.2
Summary: Easy delegation with composition
Home-page: https://github.com/hsharrison/smartcompose
Author: Henry S. Harrison
Author-email: henry.schafer.harrison@gmail.com
License: MIT
Keywords: composition delegation delegate compose
Platform: UNKNOWN
Classifier: Programming Language :: Python
Classifier: Programming Language :: Python :: 3
Classifier: License :: OSI Approved :: MIT License
Classifier: Operating System :: OS Independent
Classifier: Development Status :: 3 - Alpha
Classifier: Intended Audience :: Developers
Classifier: Topic :: Utilities
